casual_llm/__init__.py
casual_llm/config.py
casual_llm/messages.py
casual_llm/py.typed
casual_llm/tools.py
casual_llm/usage.py
casual_llm/message_converters/__init__.py
casual_llm/message_converters/anthropic.py
casual_llm/message_converters/ollama.py
casual_llm/message_converters/openai.py
casual_llm/providers/__init__.py
casual_llm/providers/anthropic.py
casual_llm/providers/base.py
casual_llm/providers/ollama.py
casual_llm/providers/openai.py
casual_llm/tool_converters/__init__.py
casual_llm/tool_converters/anthropic.py
casual_llm/tool_converters/ollama.py
casual_llm/tool_converters/openai.py
casual_llm/utils/__init__.py
casual_llm/utils/image.py
casual_llm-0.4.1.dist-info/licenses/LICENSE
casual_llm-0.4.1.dist-info/METADATA
casual_llm-0.4.1.dist-info/WHEEL
casual_llm-0.4.1.dist-info/top_level.txt
casual_llm-0.4.1.dist-info/RECORD
