Metadata-Version: 2.4
Name: casual-llm
Version: 0.4.1
Summary: Lightweight LLM provider abstraction with standardized message models
Author-email: Alex Stansfield <alex@casualgenius.com>
License: MIT
Project-URL: Homepage, https://github.com/casualgenius/casual-llm
Project-URL: Documentation, https://github.com/casualgenius/casual-llm#readme
Project-URL: Repository, https://github.com/casualgenius/casual-llm
Project-URL: Issues, https://github.com/casualgenius/casual-llm/issues
Keywords: llm,openai,ollama,ai,chatbot,casual
Classifier: Development Status :: 4 - Beta
Classifier: Intended Audience :: Developers
Classifier: License :: OSI Approved :: MIT License
Classifier: Programming Language :: Python :: 3
Classifier: Programming Language :: Python :: 3.10
Classifier: Programming Language :: Python :: 3.11
Classifier: Programming Language :: Python :: 3.12
Classifier: Topic :: Software Development :: Libraries :: Python Modules
Classifier: Topic :: Scientific/Engineering :: Artificial Intelligence
Requires-Python: >=3.10
License-File: LICENSE
Requires-Dist: pydantic>=2.0.0
Requires-Dist: ollama>=0.6.1
Requires-Dist: httpx[http2]>=0.28.1
Provides-Extra: openai
Requires-Dist: openai>=1.0.0; extra == "openai"
Provides-Extra: anthropic
Requires-Dist: anthropic>=0.20.0; extra == "anthropic"
Dynamic: license-file
